setup.py
brynq_sdk_jira/__init__.py
brynq_sdk_jira/jira.py
brynq_sdk_jira/tempo.py
brynq_sdk_jira.egg-info/PKG-INFO
brynq_sdk_jira.egg-info/SOURCES.txt
brynq_sdk_jira.egg-info/dependency_links.txt
brynq_sdk_jira.egg-info/not-zip-safe
brynq_sdk_jira.egg-info/requires.txt
brynq_sdk_jira.egg-info/top_level.txt