Metadata-Version: 1.0
Name: brynq-sdk-jira
Version: 2.1.1
Summary: JIRA wrapper from BrynQ
Home-page: UNKNOWN
Author: BrynQ
Author-email: support@brynq.com
License: BrynQ License
Platform: UNKNOWN
